bharatpe/__init__.py
bharatpe/client.py
bharatpe-0.0.4.dist-info/METADATA
bharatpe-0.0.4.dist-info/WHEEL
bharatpe-0.0.4.dist-info/top_level.txt
bharatpe-0.0.4.dist-info/RECORD
